rusty_validator-0.1.1rc3.dist-info/METADATA
rusty_validator-0.1.1rc3.dist-info/WHEEL
rusty_validator/__init__.pyi
rusty_validator/py.typed
rusty_validator/__init__.py
rusty_validator/_validator.cpython-312-x86_64-linux-gnu.so
rusty_validator-0.1.1rc3.dist-info/RECORD
