Metadata-Version: 2.3
Name: rusty-validator
Version: 0.1.1rc3
Classifier: Programming Language :: Rust
Classifier: Programming Language :: Python :: Implementation :: CPython
Classifier: Programming Language :: Python :: Implementation :: PyPy
Classifier: License :: OSI Approved :: MIT License
Classifier: Operating System :: OS Independent
Summary: A Rust-based validation library with Python bindings, leveraging the power of pyo3 and validator crates to provide robust and efficient email validation.
Keywords: rust,validation
Home-Page: https://github.com/mbalzert1978/rusty-validator
Author-email: Iorio Markus <mbalzert@gmail.com>
License: MIT License
Requires-Python: >=3.8
Project-URL: Homepage, https://github.com/mbalzert1978/rusty-validator
